devrunner/__init__.py
devrunner/cli.py
devrunner/id_gen.py
devrunner/server/__init__.py
devrunner/server/server.py
devrunner-0.1.0.dev0.dist-info/LICENSE
devrunner-0.1.0.dev0.dist-info/METADATA
devrunner-0.1.0.dev0.dist-info/WHEEL
devrunner-0.1.0.dev0.dist-info/entry_points.txt
devrunner-0.1.0.dev0.dist-info/top_level.txt
devrunner-0.1.0.dev0.dist-info/RECORD
